setup.py
tekh/__init__.py
tekh.egg-info/PKG-INFO
tekh.egg-info/SOURCES.txt
tekh.egg-info/dependency_links.txt
tekh.egg-info/entry_points.txt
tekh.egg-info/not-zip-safe
tekh.egg-info/requires.txt
tekh.egg-info/top_level.txt
tekh/tekh/CHANGES.txt_tmpl
tekh/tekh/MANIFEST.in_tmpl
tekh/tekh/README.txt_tmpl
tekh/tekh/development.ini_tmpl
tekh/tekh/production.ini_tmpl
tekh/tekh/setup.cfg_tmpl
tekh/tekh/setup.py_tmpl
tekh/tekh/zeo.conf
tekh/tekh/+package+/__init__.py_tmpl
tekh/tekh/+package+/models.py
tekh/tekh/+package+/models.pyc
tekh/tekh/+package+/tests.py_tmpl
tekh/tekh/+package+/utility.py
tekh/tekh/+package+/views.py_tmpl
tekh/tekh/+package+/static/favicon.ico
tekh/tekh/+package+/templates/index.jinja2_tmpl
tekh/tekh/+package+/templates/master.jinja2_tmpl