Metadata-Version: 1.0
Name: tekh
Version: 0.1
Summary: Tekh is a template which utilizes ZODB + ZEO for the database and other pyramid modules.
Home-page: http://www.ndmwebdesign.com
Author: Nathan McBride
Author-email: nmcbride@ndmwebdesign.com
License: MIT
Keywords: ZODB ZEO coverage nose pyramid pyramid_beaker pyramid_mailer pyramid_jinja2 beaker mailer jinja2
Platform: UNKNOWN
